setup.py
Gill/__init__.py
Gill/cli.py
Gill/cmd.py
Gill/daemon.py
Gill/loop.py
Gill/relay.py
Gill/utils.py
Gill/crypto/__init__.py
Gill/crypto/openssl.py
Gill/protocols/__init__.py
Gill/protocols/auth.py
Gill/protocols/dns.py
Gill/protocols/ea_protocol.py
Gill/protocols/events.py
Gill/protocols/socks5.py
shadowsocks_gilgamesh.egg-info/PKG-INFO
shadowsocks_gilgamesh.egg-info/SOURCES.txt
shadowsocks_gilgamesh.egg-info/dependency_links.txt
shadowsocks_gilgamesh.egg-info/entry_points.txt
shadowsocks_gilgamesh.egg-info/not-zip-safe
shadowsocks_gilgamesh.egg-info/requires.txt
shadowsocks_gilgamesh.egg-info/top_level.txt