Metadata-Version: 1.0
Name: shadowsocks-gilgamesh
Version: 0.2.5
Summary: a simple way to use mongo db, let db like dict
Home-page: https://github.com/Qingluan/.git
Author: Qingluan
Author-email: darkhackdevil@gmail.com
License: MIT
Platform: UNKNOWN
